example_package_sreesh2411/example.py
example_package_sreesh2411/init.py
example_package_sreesh2411-0.0.1.dist-info/LICENSE.rtf
example_package_sreesh2411-0.0.1.dist-info/METADATA
example_package_sreesh2411-0.0.1.dist-info/WHEEL
example_package_sreesh2411-0.0.1.dist-info/top_level.txt
example_package_sreesh2411-0.0.1.dist-info/RECORD
