Metadata-Version: 2.1
Name: example_package_sreesh2411
Version: 0.0.1
Summary: A small example package
Author-email: sreesh2411 <ksreesh@tamu.edu>
Project-URL: Homepage, https://github.com/srimenon/SAFE-Py
Project-URL: Bug Tracker, https://github.com/srimenon/SAFE-Py/issues
Classifier: Programming Language :: Python :: 3
Classifier: License :: OSI Approved :: MIT License
Classifier: Operating System :: OS Independent
Requires-Python: >=3.7
License-File: LICENSE.rtf
